intelligenticai/__init__.py
intelligenticai/agents/__init__.py
intelligenticai/agents/agent_judge.py
intelligenticai/agents/agent_print.py
intelligenticai/agents/ape_agent.py
intelligenticai/agents/auto_generate_swarm_config.py
intelligenticai/agents/consistency_agent.py
intelligenticai/agents/create_agents_from_yaml.py
intelligenticai/agents/exceptions.py
intelligenticai/agents/flexion_agent.py
intelligenticai/agents/gkp_agent.py
intelligenticai/agents/i_agent.py
intelligenticai/agents/openai_assistant.py
intelligenticai/agents/react_agent.py
intelligenticai/agents/reasoning_agents.py
intelligenticai/agents/reasoning_duo.py
intelligenticai/artifacts/__init__.py
intelligenticai/artifacts/main_artifact.py
intelligenticai/cli/__init__.py
intelligenticai/cli/main.py
intelligenticai/prompts/__init__.py
intelligenticai/prompts/accountant_swarm_prompts.py
intelligenticai/prompts/ag_prompt.py
intelligenticai/prompts/aga.py
intelligenticai/prompts/agent_conversation_aggregator.py
intelligenticai/prompts/agent_judge_prompt.py
intelligenticai/prompts/agent_orchestration_prompt.py
intelligenticai/prompts/agent_prompts.py
intelligenticai/prompts/agent_self_builder_prompt.py
intelligenticai/prompts/agent_system_prompts.py
intelligenticai/prompts/ai_research_team.py
intelligenticai/prompts/aot_prompt.py
intelligenticai/prompts/autobloggen.py
intelligenticai/prompts/autoswarm.py
intelligenticai/prompts/code_interpreter.py
intelligenticai/prompts/code_spawner.py
intelligenticai/prompts/collaborative_prompts.py
intelligenticai/prompts/debate.py
intelligenticai/prompts/documentation.py
intelligenticai/prompts/education.py
intelligenticai/prompts/finance_agent_prompt.py
intelligenticai/prompts/finance_agent_sys_prompt.py
intelligenticai/prompts/growth_agent_prompt.py
intelligenticai/prompts/hiearchical_system_prompt.py
intelligenticai/prompts/idea2img.py
intelligenticai/prompts/legal_agent_prompt.py
intelligenticai/prompts/logistics.py
intelligenticai/prompts/max_loop_prompt.py
intelligenticai-2.0.1.dist-info/entry_points.txt
intelligenticai-2.0.1.dist-info/LICENSE
intelligenticai-2.0.1.dist-info/METADATA
intelligenticai-2.0.1.dist-info/WHEEL
intelligenticai-2.0.1.dist-info/RECORD
